vault_dev/__about__.py
vault_dev/__init__.py
vault_dev/install.py
vault_dev/server.py
vault_dev/utils.py
vault_dev-0.1.1.dist-info/METADATA
vault_dev-0.1.1.dist-info/WHEEL
vault_dev-0.1.1.dist-info/licenses/LICENSE.txt
vault_dev-0.1.1.dist-info/RECORD
