Metadata-Version: 2.1
Name: vault-dev
Version: 0.1.1
Project-URL: Documentation, https://github.com/vimc/vault-dev#readme
Project-URL: Issues, https://github.com/vimc/vault-dev/issues
Project-URL: Source, https://github.com/vimc/vault-dev
Author-email: Rich FitzJohn <r.fitzjohn@imperial.ac.uk>
License-Expression: MIT
License-File: LICENSE.txt
Classifier: Development Status :: 4 - Beta
Classifier: Programming Language :: Python
Classifier: Programming Language :: Python :: 3.7
Classifier: Programming Language :: Python :: 3.8
Classifier: Programming Language :: Python :: 3.9
Classifier: Programming Language :: Python :: 3.10
Classifier: Programming Language :: Python :: 3.11
Classifier: Programming Language :: Python :: Implementation :: CPython
Classifier: Programming Language :: Python :: Implementation :: PyPy
Requires-Python: >=3.7
Requires-Dist: deprecated
Requires-Dist: hvac
Requires-Dist: requests
